<?xml version="1.0" encoding="UTF-8"?>
<!DOCTYPE hibernate-mapping PUBLIC "-//Hibernate/Hibernate Mapping DTD 3.0//EN" "http://hibernate.sourceforge.net/hibernate-mapping-3.0.dtd">
<hibernate-mapping>
  <class name="com.ghxt.pojo.Aabcsb" table="AA002">
            <id name="aab001" type="java.lang.String" >
    	<column name="AAB001" length="20"/>
      <generator class="assigned"/>
    </id>
                                                                                                    
		<property name="aab002" type="java.lang.String"><column name="AAB002" length="10"/></property>      
		<property name="aab003" type="java.lang.String"><column name="AAB003" length="20"/></property>      
		<property name="aab004" type="java.math.BigDecimal"><column name="AAB004" length="12"/></property>  
		<property name="aab005" type="java.lang.String"><column name="AAB005" length="1"/></property>       
		<property name="aab006" type="java.lang.String"><column name="AAB006" length="100"/></property>     
		<property name="aab007" type="java.lang.String"><column name="AAB007" length="1"/></property>       
		<property name="aab008" type="java.lang.String"><column name="AAB008" length="1"/></property>       
		<property name="aab009" type="java.math.BigDecimal"><column name="AAB009" length="12"/></property>  
		<property name="aab010" type="java.math.BigDecimal"><column name="AAB010" length="12"/></property>  

          </class>
</hibernate-mapping>